<?xml version="1.0" encoding="utf-8"?>
<abapGit version="v1.0.0" serializer="LCL_OBJECT_SHI3" serializer_version="v1.0.0">
 <asx:abap xmlns:asx="http://www.sap.com/abapxml" version="1.0">
  <asx:values>
   <TREE_HEAD>
    <ID>ZSD00</ID>
    <TYPE>BMENU</TYPE>
    <NODE_ID>ZSD00_T</NODE_ID>
    <MASTERLANG>T</MASTERLANG>
    <BUFFERMODE>1</BUFFERMODE>
   </TREE_HEAD>
   <TREE_TITLES>
    <TTREET>
     <SPRAS>T</SPRAS>
     <ID>ZSD00</ID>
     <TEXT>SD Uyarlama Menüsü</TEXT>
     <TEXT_CAP>SD UYARLAMA MENÜSÜ</TEXT_CAP>
    </TTREET>
   </TREE_TITLES>
   <TREE_NODES>
    <HIER_IFACE>
     <NODE_ID>ZSD00_T</NODE_ID>
     <NODE_TYPE>NULL</NODE_TYPE>
     <NODE_LEVEL>01</NODE_LEVEL>
     <TREE_ID>ZSD00</TREE_ID>
     <FORCE_PLUS>X</FORCE_PLUS>
     <COPY_NODE>ZYB_SD00_T</COPY_NODE>
     <COPY_TREE>ZYB_SD00</COPY_TREE>
     <COPNODFRST>ZYB_SD00_T</COPNODFRST>
     <COPTREFRST>ZYB_SD00</COPTREFRST>
    </HIER_IFACE>
    <HIER_IFACE>
     <NODE_ID>005056AF698E1ED581C122C20781B40B</NODE_ID>
     <NODE_TYPE>NULL</NODE_TYPE>
     <NODE_LEVEL>02</NODE_LEVEL>
     <PARENT_ID>ZSD00_T</PARENT_ID>
     <TREE_ID>ZSD00</TREE_ID>
     <FORCE_PLUS>X</FORCE_PLUS>
     <COPY_NODE>005056AF698E1ED4A9F77C9DADD83403</COPY_NODE>
     <COPY_TREE>ZYB_SD00</COPY_TREE>
     <COPNODFRST>005056AF698E1ED4A9F77C9DADD83403</COPNODFRST>
     <COPTREFRST>ZYB_SD00</COPTREFRST>
    </HIER_IFACE>
    <HIER_IFACE>
     <NODE_ID>005056AF698E1ED581D70BB526AAF40B</NODE_ID>
     <NODE_TYPE>TCOD</NODE_TYPE>
     <NODE_LEVEL>03</NODE_LEVEL>
     <PARENT_ID>005056AF698E1ED581C122C20781B40B</PARENT_ID>
     <TREE_ID>ZSD00</TREE_ID>
    </HIER_IFACE>
    <HIER_IFACE>
     <NODE_ID>005056AF698E1ED58D8C8D38DE83541E</NODE_ID>
     <NODE_TYPE>TCOD</NODE_TYPE>
     <NODE_LEVEL>03</NODE_LEVEL>
     <PARENT_ID>005056AF698E1ED581C122C20781B40B</PARENT_ID>
     <BROTHER_ID>005056AF698E1ED581D70BB526AAF40B</BROTHER_ID>
     <TREE_ID>ZSD00</TREE_ID>
    </HIER_IFACE>
    <HIER_IFACE>
     <NODE_ID>005056AF698E1ED581D70BB526AB140B</NODE_ID>
     <NODE_TYPE>TCOD</NODE_TYPE>
     <NODE_LEVEL>03</NODE_LEVEL>
     <PARENT_ID>005056AF698E1ED581C122C20781B40B</PARENT_ID>
     <BROTHER_ID>005056AF698E1ED58D8C8D38DE83541E</BROTHER_ID>
     <TREE_ID>ZSD00</TREE_ID>
    </HIER_IFACE>
    <HIER_IFACE>
     <NODE_ID>005056AF698E1ED581C122C20781D40B</NODE_ID>
     <NODE_TYPE>TCOD</NODE_TYPE>
     <NODE_LEVEL>03</NODE_LEVEL>
     <PARENT_ID>005056AF698E1ED581C122C20781B40B</PARENT_ID>
     <BROTHER_ID>005056AF698E1ED581D70BB526AB140B</BROTHER_ID>
     <TREE_ID>ZSD00</TREE_ID>
     <COPY_NODE>005056AF698E1ED4A9F77DF643407403</COPY_NODE>
     <COPY_TREE>ZYB_SD00</COPY_TREE>
     <COPNODFRST>005056AF698E1ED4A9F77DF643407403</COPNODFRST>
     <COPTREFRST>ZYB_SD00</COPTREFRST>
    </HIER_IFACE>
    <HIER_IFACE>
     <NODE_ID>005056AF698E1ED581C122C20781F40B</NODE_ID>
     <NODE_TYPE>NULL</NODE_TYPE>
     <NODE_LEVEL>02</NODE_LEVEL>
     <PARENT_ID>ZSD00_T</PARENT_ID>
     <BROTHER_ID>005056AF698E1ED581C122C20781B40B</BROTHER_ID>
     <TREE_ID>ZSD00</TREE_ID>
     <FORCE_PLUS>X</FORCE_PLUS>
     <COPY_NODE>005056AF698E1ED4A9F836B1DB793403</COPY_NODE>
     <COPY_TREE>ZYB_SD00</COPY_TREE>
     <COPNODFRST>005056AF698E1ED4A9F836B1DB793403</COPNODFRST>
     <COPTREFRST>ZYB_SD00</COPTREFRST>
    </HIER_IFACE>
    <HIER_IFACE>
     <NODE_ID>005056AF698E1ED581C122C20782140B</NODE_ID>
     <NODE_TYPE>TCOD</NODE_TYPE>
     <NODE_LEVEL>03</NODE_LEVEL>
     <PARENT_ID>005056AF698E1ED581C122C20781F40B</PARENT_ID>
     <TREE_ID>ZSD00</TREE_ID>
     <COPY_NODE>005056AF698E1ED4A9F846FD3BE81403</COPY_NODE>
     <COPY_TREE>ZYB_SD00</COPY_TREE>
     <COPNODFRST>005056AF698E1ED4A9F846FD3BE81403</COPNODFRST>
     <COPTREFRST>ZYB_SD00</COPTREFRST>
    </HIER_IFACE>
    <HIER_IFACE>
     <NODE_ID>005056AF698E1ED581C122C20782340B</NODE_ID>
     <NODE_TYPE>TCOD</NODE_TYPE>
     <NODE_LEVEL>02</NODE_LEVEL>
     <PARENT_ID>ZSD00_T</PARENT_ID>
     <BROTHER_ID>005056AF698E1ED581C122C20781F40B</BROTHER_ID>
     <TREE_ID>ZSD00</TREE_ID>
     <COPY_NODE>005056AF698E1ED4BBFCAA6DD2609407</COPY_NODE>
     <COPY_TREE>ZYB_SD00</COPY_TREE>
     <COPNODFRST>005056AF698E1ED4BBFCAA6DD2609407</COPNODFRST>
     <COPTREFRST>ZYB_SD00</COPTREFRST>
    </HIER_IFACE>
    <HIER_IFACE>
     <NODE_ID>005056AF698E1ED58793C2957EEF7412</NODE_ID>
     <NODE_TYPE>TCOD</NODE_TYPE>
     <NODE_LEVEL>02</NODE_LEVEL>
     <PARENT_ID>ZSD00_T</PARENT_ID>
     <BROTHER_ID>005056AF698E1ED581C122C20782340B</BROTHER_ID>
     <TREE_ID>ZSD00</TREE_ID>
    </HIER_IFACE>
    <HIER_IFACE>
     <NODE_ID>005056AF698E1ED884CFA8042EE7145D</NODE_ID>
     <NODE_TYPE>TCOD</NODE_TYPE>
     <NODE_LEVEL>02</NODE_LEVEL>
     <PARENT_ID>ZSD00_T</PARENT_ID>
     <BROTHER_ID>005056AF698E1ED58793C2957EEF7412</BROTHER_ID>
     <TREE_ID>ZSD00</TREE_ID>
    </HIER_IFACE>
   </TREE_NODES>
   <TREE_REFS>
    <HIER_REF>
     <NODE_ID>005056AF698E1ED581C122C20781B40B</NODE_ID>
     <REF_TYPE>BMFR</REF_TYPE>
     <REF_OBJECT>HLA0009999</REF_OBJECT>
    </HIER_REF>
    <HIER_REF>
     <NODE_ID>005056AF698E1ED581C122C20781D40B</NODE_ID>
     <REF_TYPE>BMFR</REF_TYPE>
     <REF_OBJECT>HLA0009999</REF_OBJECT>
    </HIER_REF>
    <HIER_REF>
     <NODE_ID>005056AF698E1ED581C122C20781D40B</NODE_ID>
     <REF_TYPE>TCOD</REF_TYPE>
     <REF_OBJECT>ZSD001</REF_OBJECT>
    </HIER_REF>
    <HIER_REF>
     <NODE_ID>005056AF698E1ED581C122C20781F40B</NODE_ID>
     <REF_TYPE>BMFR</REF_TYPE>
     <REF_OBJECT>HLA0009999</REF_OBJECT>
    </HIER_REF>
    <HIER_REF>
     <NODE_ID>005056AF698E1ED581C122C20782140B</NODE_ID>
     <REF_TYPE>BMFR</REF_TYPE>
     <REF_OBJECT>HLA0009999</REF_OBJECT>
    </HIER_REF>
    <HIER_REF>
     <NODE_ID>005056AF698E1ED581C122C20782140B</NODE_ID>
     <REF_TYPE>TCOD</REF_TYPE>
     <REF_OBJECT>ZSD002</REF_OBJECT>
    </HIER_REF>
    <HIER_REF>
     <NODE_ID>005056AF698E1ED581C122C20782340B</NODE_ID>
     <REF_TYPE>BMFR</REF_TYPE>
     <REF_OBJECT>HLA0009999</REF_OBJECT>
    </HIER_REF>
    <HIER_REF>
     <NODE_ID>005056AF698E1ED581C122C20782340B</NODE_ID>
     <REF_TYPE>TCOD</REF_TYPE>
     <REF_OBJECT>ZSD003</REF_OBJECT>
    </HIER_REF>
    <HIER_REF>
     <NODE_ID>005056AF698E1ED581D70BB526AAF40B</NODE_ID>
     <REF_TYPE>BMFR</REF_TYPE>
     <REF_OBJECT>HLA0009999</REF_OBJECT>
    </HIER_REF>
    <HIER_REF>
     <NODE_ID>005056AF698E1ED581D70BB526AAF40B</NODE_ID>
     <REF_TYPE>TCOD</REF_TYPE>
     <REF_OBJECT>ZSD005</REF_OBJECT>
    </HIER_REF>
    <HIER_REF>
     <NODE_ID>005056AF698E1ED581D70BB526AB140B</NODE_ID>
     <REF_TYPE>BMFR</REF_TYPE>
     <REF_OBJECT>HLA0009999</REF_OBJECT>
    </HIER_REF>
    <HIER_REF>
     <NODE_ID>005056AF698E1ED581D70BB526AB140B</NODE_ID>
     <REF_TYPE>TCOD</REF_TYPE>
     <REF_OBJECT>ZSD006</REF_OBJECT>
    </HIER_REF>
    <HIER_REF>
     <NODE_ID>005056AF698E1ED58793C2957EEF7412</NODE_ID>
     <REF_TYPE>BMFR</REF_TYPE>
     <REF_OBJECT>HLA0009999</REF_OBJECT>
    </HIER_REF>
    <HIER_REF>
     <NODE_ID>005056AF698E1ED58793C2957EEF7412</NODE_ID>
     <REF_TYPE>TCOD</REF_TYPE>
     <REF_OBJECT>ZSD012</REF_OBJECT>
    </HIER_REF>
    <HIER_REF>
     <NODE_ID>005056AF698E1ED58D8C8D38DE83541E</NODE_ID>
     <REF_TYPE>BMFR</REF_TYPE>
     <REF_OBJECT>HLA0009999</REF_OBJECT>
    </HIER_REF>
    <HIER_REF>
     <NODE_ID>005056AF698E1ED58D8C8D38DE83541E</NODE_ID>
     <REF_TYPE>TCOD</REF_TYPE>
     <REF_OBJECT>ZSD102</REF_OBJECT>
    </HIER_REF>
    <HIER_REF>
     <NODE_ID>005056AF698E1ED884CFA8042EE7145D</NODE_ID>
     <REF_TYPE>BMFR</REF_TYPE>
     <REF_OBJECT>HLA0009999</REF_OBJECT>
    </HIER_REF>
    <HIER_REF>
     <NODE_ID>005056AF698E1ED884CFA8042EE7145D</NODE_ID>
     <REF_TYPE>TCOD</REF_TYPE>
     <REF_OBJECT>ZSD033</REF_OBJECT>
    </HIER_REF>
   </TREE_REFS>
   <TREE_TEXTS>
    <HIER_TEXTS>
     <SPRAS>T</SPRAS>
     <NODE_ID>005056AF698E1ED581C122C20781B40B</NODE_ID>
     <TEXT>Malzeme</TEXT>
    </HIER_TEXTS>
    <HIER_TEXTS>
     <SPRAS>T</SPRAS>
     <NODE_ID>005056AF698E1ED581C122C20781D40B</NODE_ID>
     <TEXT>Mlz. Ana. Org. Kntrlü Uyarlaması</TEXT>
    </HIER_TEXTS>
    <HIER_TEXTS>
     <SPRAS>T</SPRAS>
     <NODE_ID>005056AF698E1ED581C122C20781F40B</NODE_ID>
     <TEXT>Müşteri</TEXT>
    </HIER_TEXTS>
    <HIER_TEXTS>
     <SPRAS>T</SPRAS>
     <NODE_ID>005056AF698E1ED581C122C20782140B</NODE_ID>
     <TEXT>Müş. Ana. Org. Kntrlü Uyarlaması</TEXT>
    </HIER_TEXTS>
    <HIER_TEXTS>
     <SPRAS>T</SPRAS>
     <NODE_ID>005056AF698E1ED581C122C20782340B</NODE_ID>
     <TEXT>Parti Krk / İşlem  Bakım Tablosu</TEXT>
    </HIER_TEXTS>
    <HIER_TEXTS>
     <SPRAS>T</SPRAS>
     <NODE_ID>005056AF698E1ED581D70BB526AAF40B</NODE_ID>
     <TEXT>Mamül Palet/Kutu Miktar Bakımı</TEXT>
    </HIER_TEXTS>
    <HIER_TEXTS>
     <SPRAS>T</SPRAS>
     <NODE_ID>005056AF698E1ED581D70BB526AB140B</NODE_ID>
     <TEXT>Müşteri - Malzeme Palet Kutu Bilgisi</TEXT>
    </HIER_TEXTS>
    <HIER_TEXTS>
     <SPRAS>T</SPRAS>
     <NODE_ID>005056AF698E1ED58793C2957EEF7412</NODE_ID>
     <TEXT>Mail Bakım</TEXT>
    </HIER_TEXTS>
    <HIER_TEXTS>
     <SPRAS>T</SPRAS>
     <NODE_ID>005056AF698E1ED58D8C8D38DE83541E</NODE_ID>
     <TEXT>Palet Düz. Malz. Ölçü Dönüşüm Raporu</TEXT>
    </HIER_TEXTS>
    <HIER_TEXTS>
     <SPRAS>T</SPRAS>
     <NODE_ID>005056AF698E1ED884CFA8042EE7145D</NODE_ID>
     <TEXT>Satış Fat. için Masraf Yeri Atama</TEXT>
    </HIER_TEXTS>
    <HIER_TEXTS>
     <SPRAS>T</SPRAS>
     <NODE_ID>ZSD00_T</NODE_ID>
     <TEXT>SD Uyarlama Menüsü</TEXT>
    </HIER_TEXTS>
   </TREE_TEXTS>
  </asx:values>
 </asx:abap>
</abapGit>
